{
    "phone": "+33780093303",
    "email": "admin@dev1lroot.com",
    "country": "FR",
    "city": "Saint-Brieuc",
    "dob": "1999-04-25",
    "name": {
        "en-GB": "David von Eichendorf",
        "es-ES": "David von Eichendorf",
        "fr-FR": "David von Eichendorf",
        "de-DE": "David von Eichendorf",
        "uk-UA": "Девід фон Айхендорф",
        "ru-RU": "Дэвид Эйхендорф",
        "he-IL": "דוד פון איכנדורף",
        "ar-AE": "ديفيد فون آيشندورف",
        "hi-IN": "डेविड वॉन आइचेंडॉर्फ़",
        "zh-CN": "大卫·冯·艾亨多夫",
        "ko-KR": "데이비드 폰 아이헨도르프",
        "ja-JP": "デイビッド・フォン・アイヒェンドルフ"
    },
    "description": {
        "en-GB": "ABDL 🌈 | Gay 🏳️‍🌈 | Software Developer ⚙️ | Refugee 🇫🇷 | Founder of Adultbaby.ru | Creator of SIZO-SIM | I Stand with Ukraine 🇺🇦",
        "es-ES": "ABDL 🌈 | Gay 🏳️‍🌈 | Desarrollador de software ⚙️ | Refugiado 🇫🇷 | Fundador de Adultbaby.ru | Creador de SIZO-SIM | Apoyo a Ucrania 🇺🇦",
        "fr-FR": "ABDL 🌈 | Gay 🏳️‍🌈 | Programmeur ⚙️ | Réfugié en 🇫🇷 | Fondateur d'Adultbaby.ru | Créateur de SIZO-SIM | Né en 🇷🇺 | Soutien à l'Ukraine 🇺🇦",
        "de-DE": "ABDL 🌈 | Schwul 🏳️‍🌈 | Softwareentwickler ⚙️ | Flüchtling 🇫🇷 | Gründer von Adultbaby.ru | Ersteller von SIZO-SIM | Unterstütze die Ukraine 🇺🇦",
        "uk-UA": "ABDL 🌈 | Гей 🏳️‍🌈 | Розробник програмного забезпечення ⚙️ | Біженець у 🇫🇷 | Засновник Adultbaby.ru | Створювач SIZO-SIM | Підтримую Україну 🇺🇦",
        "ru-RU": "АБДЛ 🌈 | Гей 🏳️‍🌈 | Программист ⚙️ | Беженец во 🇫🇷 | Основатель Adultbaby.ru | Создатель SIZO-SIM | Поддерживаю Украину 🇺🇦 | Родился в 🇷🇺",
        "he-IL": "ABDL 🌈 | גיי 🏳️‍🌈 | מפתח תוכנה ⚙️ | פליט 🇫🇷 | מייסד Adultbaby.ru | יוצר SIZO-SIM | תומך באוקראינה 🇺🇦",
        "ar-AE": "ABDL 🌈 | مثلي 🏳️‍🌈 | مطور برامج ⚙️ | لاجئ 🇫🇷 | مؤسس Adultbaby.ru | منشئ SIZO-SIM | أؤيد أوكرانيا 🇺🇦",
        "hi-IN": "ABDL 🌈 | गे 🏳️‍🌈 | सॉफ़्टवेयर डेवलपर ⚙️ | शरणार्थी 🇫🇷 | Adultbaby.ru के संस्थापक | SIZO-SIM के निर्माता | मैं यूक्रेन के साथ हूँ 🇺🇦",
        "zh-CN": "ABDL 🌈 | 同性恋 🏳️‍🌈 | 软件开发者 ⚙️ | 难民 🇫🇷 | Adultbaby.ru 创始人 | SIZO-SIM 创作者 | 支持乌克兰 🇺🇦",
        "ko-KR": "ABDL 🌈 | 게이 🏳️‍🌈 | 소프트웨어 개발자 ⚙️ | 난민 🇫🇷 | Adultbaby.ru 설립자 | SIZO-SIM 제작자 | 우크라이나를 지지합니다 🇺🇦",
        "ja-JP": "ABDL 🌈 | ゲイ 🏳️‍🌈 | ソフトウェア開発者 ⚙️ | 難民 🇫🇷 | Adultbaby.ru 創設者 | SIZO-SIM 作成者 | ウクライナを支援 🇺🇦"
    },
    "bio": {
        "ru-RU": ""
    }
}
